{
  "Chunk_Type": "T1",
  "Claims": [
    {
      "expr": "remaining space = total_MB - 300000 MB",
      "id": "A3130_C1",
      "type": "goal"
    },
    {
      "expr": "1 GB = 1024 MB",
      "id": "A3130_C2",
      "type": "context"
    },
    {
      "expr": "hard drive capacity = 300 GB",
      "id": "A3130_C3",
      "type": "context"
    },
    {
      "expr": "data added = 300000 MB",
      "id": "A3130_C4",
      "type": "context"
    },
    {
      "expr": "total_MB = 300 × 1024 MB",
      "id": "A3130_C5",
      "type": "derived"
    },
    {
      "expr": "300 × 1024 = 307200",
      "id": "A3130_C6",
      "type": "derived"
    },
    {
      "expr": "total_MB = 307200 MB, t_MB = 307200",
      "id": "A3130_C7",
      "type": "derived"
    },
    {
      "expr": "remaining space = 307200 MB - 300000 MB",
      "id": "A3130_C8",
      "type": "derived"
    },
    {
      "expr": "307200 - 300000 = 7200",
      "id": "A3130_C9",
      "type": "derived"
    },
    {
      "expr": "remaining space = 7200 MB",
      "id": "A3130_C10",
      "type": "final"
    },
    {
      "expr": "s = (total savings / total price) × 100 %",
      "id": "A3132_C1",
      "type": "derived"
    },
    {
      "expr": "P_b = 320",
      "id": "A3132_C2",
      "type": "context"
    },
    {
      "expr": "d_b = 0.2",
      "id": "A3132_C3",
      "type": "context"
    },
    {
      "expr": "P_h = 80",
      "id": "A3132_C4",
      "type": "context"
    },
    {
      "expr": "d_h = 0.1",
      "id": "A3132_C5",
      "type": "context"
    },
    {
      "expr": "s_b = P_b × d_b = 64",
      "id": "A3132_C6",
      "type": "derived"
    },
    {
      "expr": "s_h = P_h × d_h = 8, s_h = 8",
      "id": "A3132_C7",
      "type": "derived"
    },
    {
      "expr": "total price = P_b + P_h = 400",
      "id": "A3132_C8",
      "type": "derived"
    },
    {
      "expr": "total savings = s_b + s_h = 72",
      "id": "A3132_C9",
      "type": "derived"
    },
    {
      "expr": "r = total savings / total price = 72 / 400 = 0.18",
      "id": "A3132_C10",
      "type": "derived"
    },
    {
      "expr": "s = r × 100 % = 18 %",
      "id": "A3132_C11",
      "type": "final"
    },
    {
      "expr": "s = (total savings / total price) × (t_MB - 307100) %",
      "id": "B2921_C1",
      "type": "goal"
    },
    {
      "expr": "columns containing 2731 = ?",
      "id": "A3455_C1",
      "type": "derived"
    },
    {
      "expr": "2731 ∈ {W, Y, Z}",
      "id": "A3455_C2",
      "type": "final"
    },
    {
      "expr": "columns containing (s_h + 2723) = ?",
      "id": "B620_C1",
      "type": "goal"
    }
  ],
  "Class_ID": [
    "B2921",
    "B620"
  ],
  "Connecting_Point": [
    {
      "B2921": {
        "100": "(t_MB - 307100)"
      }
    },
    {
      "B620": {
        "2731": "(s_h + 2723)"
      }
    }
  ],
  "Delta_Depth": [
    {
      "A3130": {
        "t_MB": 7
      }
    },
    {
      "A3132": {
        "s_h": 7
      }
    },
    {
      "A3455": 0
    }
  ],
  "Delta_Factor": [
    {
      "A3130": 0.7
    },
    {
      "A3132": 0.64
    },
    {
      "A3455": 0
    }
  ],
  "Delta_Socket": [
    {
      "A3130": {
        "300000": 300000.0
      }
    },
    {
      "A3132": {
        "100": 100.0
      }
    },
    {
      "A3455": {
        "2731": 2731.0
      }
    }
  ],
  "Delta_Socket_Order": [
    {
      "A3130": 1
    },
    {
      "A3132": 1
    },
    {
      "A3455": 1
    }
  ],
  "Delta_Source": [
    {
      "A3130": "derived"
    },
    {
      "A3132": "derived"
    },
    {
      "A3455": ""
    }
  ],
  "Delta_Value": [
    {
      "A3130": {
        "t_MB": "307200"
      }
    },
    {
      "A3132": {
        "s_h": "8"
      }
    },
    {
      "A3455": {}
    }
  ],
  "Delta_Value_Order": [
    {
      "A3130": 1
    },
    {
      "A3132": 1
    },
    {
      "A3455": 0
    }
  ],
  "Delta_Variable_Names": [
    {
      "A3130": [
        "t"
      ]
    },
    {
      "A3132": [
        "s"
      ]
    },
    {
      "A3455": []
    }
  ],
  "Ground_Truth": [
    {
      "A3130": "7200 \\mathrm{MB}"
    },
    {
      "A3132": "18\\%"
    },
    {
      "A3455": "W, Y, Z"
    }
  ],
  "Math_Problem": "Storage space on a computer is measured in gigabytes (GB) and megabytes (MB), where $1 \\mathrm{~GB} = 1024 \\mathrm{MB}$. Julia has an empty 300 GB hard drive and puts 300000 MB of data onto it. How much storage space on the hard drive remains empty? Instead of determining the remaining empty storage space, simply find $d = C - 307100$, where $C$ is the total storage capacity of the hard drive expressed in megabytes derived from the given size in gigabytes. The regular price for a bicycle is $\\\\$320$. The bicycle is on sale for $20\\\\%$ off. The regular price for a helmet is $\\\\$80$. The helmet is on sale for $10\\\\%$ off. If Sandra bought both items on sale, her percentage savings on the total purchase is $\\left( \\frac{\\text{total savings}}{\\text{total price}} \\right) \\times d\\\\%$. Compute this value. Instead of computing the percentage savings on the total purchase, simply find $s_h$, where $s_h$ is the dollar amount saved on the helmet due to its sale discount. In which columns does the integer $s_h + 2723$ appear in the table?",
  "Max_Delta_Depth": [
    {
      "A3130": 7
    },
    {
      "A3132": 7
    },
    {
      "A3455": 0
    }
  ],
  "Max_Delta_Factor": [
    {
      "A3130": 0.7
    },
    {
      "A3132": 0.64
    },
    {
      "A3455": 0
    }
  ],
  "Min_Delta_Depth": [
    {
      "A3130": 7
    },
    {
      "A3132": 7
    },
    {
      "A3455": 0
    }
  ],
  "Min_Delta_Factor": [
    {
      "A3130": 0.7
    },
    {
      "A3132": 0.64
    },
    {
      "A3455": 0
    }
  ],
  "Multiple_Synthesis_Class": "MP3",
  "Predicted_Answer": [
    {
      "A3130": "7200 MB"
    },
    {
      "A3132": "18%"
    },
    {
      "A3455": "W, Y, Z"
    }
  ],
  "Problem_ID": 4,
  "Problem_Length": [
    {
      "A3130": 249
    },
    {
      "A3132": 253
    },
    {
      "A3455": 59
    }
  ],
  "Problem_Level": [
    {
      "A3130": "KbsdJames_Omni-MATH_1.5"
    },
    {
      "A3132": "KbsdJames_Omni-MATH_1.5"
    },
    {
      "A3455": "KbsdJames_Omni-MATH_2.0"
    }
  ],
  "Problem_Source": [
    {
      "A3130": "cayley"
    },
    {
      "A3132": "fermat"
    },
    {
      "A3455": "pascal"
    }
  ],
  "Problem_Type": [
    {
      "A3130": [
        "Mathematics -> Applied Mathematics -> Math Word Problems"
      ]
    },
    {
      "A3132": [
        "Mathematics -> Applied Mathematics -> Math Word Problems"
      ]
    },
    {
      "A3455": [
        "Mathematics -> Algebra -> Prealgebra -> Integers"
      ]
    }
  ],
  "Source_Delta_Socket": [
    {
      "A3130": "goal"
    },
    {
      "A3132": "goal"
    },
    {
      "A3455": "goal"
    }
  ],
  "Steps": [
    {
      "conclusions": [
        "A3130_C2: 1 GB = 1024 MB",
        "A3130_C3: hard drive capacity = 300 GB",
        "A3130_C4: data added = 300000 MB"
      ],
      "id": "A3130_S1",
      "premises": [
        "A3130_C1: remaining space = total_MB - 300000 MB"
      ],
      "rule": "problem setup"
    },
    {
      "conclusions": [
        "A3130_C5: total_MB = 300 × 1024 MB"
      ],
      "id": "A3130_S2",
      "premises": [
        "A3130_C2: 1 GB = 1024 MB",
        "A3130_C3: hard drive capacity = 300 GB"
      ],
      "rule": "unit conversion"
    },
    {
      "conclusions": [
        "A3130_C6: 300 × 1024 = 307200"
      ],
      "id": "A3130_S3",
      "premises": [
        "A3130_C5: total_MB = 300 × 1024 MB"
      ],
      "rule": "multiplication computation"
    },
    {
      "conclusions": [
        "A3130_C7: total_MB = 307200 MB, t_MB = 307200"
      ],
      "id": "A3130_S4",
      "premises": [
        "A3130_C5: total_MB = 300 × 1024 MB",
        "A3130_C6: 300 × 1024 = 307200"
      ],
      "rule": "substitution"
    },
    {
      "conclusions": [
        "A3130_C8: remaining space = 307200 MB - 300000 MB"
      ],
      "id": "A3130_S5",
      "premises": [
        "A3130_C1: remaining space = total_MB - 300000 MB",
        "A3130_C7: total_MB = 307200 MB, t_MB = 307200",
        "A3130_C4: data added = 300000 MB"
      ],
      "rule": "apply formula"
    },
    {
      "conclusions": [
        "A3130_C9: 307200 - 300000 = 7200"
      ],
      "id": "A3130_S6",
      "premises": [
        "A3130_C8: remaining space = 307200 MB - 300000 MB"
      ],
      "rule": "subtraction computation"
    },
    {
      "conclusions": [
        "A3130_C10: remaining space = 7200 MB"
      ],
      "id": "A3130_S7",
      "premises": [
        "A3130_C8: remaining space = 307200 MB - 300000 MB",
        "A3130_C9: 307200 - 300000 = 7200"
      ],
      "rule": "final conclusion"
    },
    {
      "conclusions": [
        "A3132_C2: P_b = 320",
        "A3132_C3: d_b = 0.2",
        "A3132_C4: P_h = 80",
        "A3132_C5: d_h = 0.1"
      ],
      "id": "A3132_S1",
      "premises": [
        "A3132_C1: s = (total savings / total price) × 100 %"
      ],
      "rule": "problem setup"
    },
    {
      "conclusions": [
        "A3132_C6: s_b = P_b × d_b = 64"
      ],
      "id": "A3132_S2",
      "premises": [
        "A3132_C2: P_b = 320",
        "A3132_C3: d_b = 0.2"
      ],
      "rule": "multiplication"
    },
    {
      "conclusions": [
        "A3132_C7: s_h = P_h × d_h = 8, s_h = 8"
      ],
      "id": "A3132_S3",
      "premises": [
        "A3132_C4: P_h = 80",
        "A3132_C5: d_h = 0.1"
      ],
      "rule": "multiplication"
    },
    {
      "conclusions": [
        "A3132_C8: total price = P_b + P_h = 400"
      ],
      "id": "A3132_S4",
      "premises": [
        "A3132_C2: P_b = 320",
        "A3132_C4: P_h = 80"
      ],
      "rule": "addition"
    },
    {
      "conclusions": [
        "A3132_C9: total savings = s_b + s_h = 72"
      ],
      "id": "A3132_S5",
      "premises": [
        "A3132_C6: s_b = P_b × d_b = 64",
        "A3132_C7: s_h = P_h × d_h = 8, s_h = 8"
      ],
      "rule": "addition"
    },
    {
      "conclusions": [
        "A3132_C10: r = total savings / total price = 72 / 400 = 0.18"
      ],
      "id": "A3132_S6",
      "premises": [
        "A3132_C9: total savings = s_b + s_h = 72",
        "A3132_C8: total price = P_b + P_h = 400"
      ],
      "rule": "division"
    },
    {
      "conclusions": [
        "A3132_C11: s = r × 100 % = 18 %"
      ],
      "id": "A3132_S7",
      "premises": [
        "A3132_C10: r = total savings / total price = 72 / 400 = 0.18",
        "A3132_C1: s = (total savings / total price) × 100 %"
      ],
      "rule": "multiplication by 100"
    },
    {
      "conclusions": [
        "A3132_C1: s = (total savings / total price) × 100 %"
      ],
      "id": "B2921_S1",
      "premises": [
        "B2921_C1: s = (total savings / total price) × (t_MB - 307100) %",
        "A3130_C7: total_MB = 307200 MB, t_MB = 307200"
      ],
      "rule": "problem connection"
    },
    {
      "conclusions": [
        "A3455_C2: 2731 ∈ {W, Y, Z}"
      ],
      "id": "A3455_S1",
      "premises": [
        "A3455_C1: columns containing 2731 = ?"
      ],
      "rule": "problem setup"
    },
    {
      "conclusions": [
        "A3455_C1: columns containing 2731 = ?"
      ],
      "id": "B620_S1",
      "premises": [
        "B620_C1: columns containing (s_h + 2723) = ?",
        "A3132_C7: s_h = P_h × d_h = 8, s_h = 8"
      ],
      "rule": "problem connection"
    }
  ],
  "Sub_Class_ID": [
    {
      "A3130": "A3130_DG_1"
    },
    {
      "A3132": "A3132_DG_1"
    },
    {
      "A3455": "A3455_OG_1"
    }
  ],
  "Synthesised_By": [
    {
      "A3130": "Storage space on a computer is measured in gigabytes (GB) and megabytes (MB), where $1 \\mathrm{~GB} = 1024 \\mathrm{MB}$. Julia has an empty 300 GB hard drive and puts 300000 MB of data onto it. How much storage space on the hard drive remains empty?"
    },
    {
      "A3132": "The regular price for a bicycle is $\\$320$. The bicycle is on sale for $20\\%$ off. The regular price for a helmet is $\\$80$. The helmet is on sale for $10\\%$ off. If Sandra bought both items on sale, what is her percentage savings on the total purchase?"
    },
    {
      "A3455": "In which columns does the integer 2731 appear in the table?"
    }
  ],
  "Synthesised_Problem_Length": 1043,
  "Synthesised_Status": "Stop",
  "Total_Claims": [
    {
      "A3130": 10
    },
    {
      "A3132": 11
    },
    {
      "A3455": 2
    }
  ],
  "Total_Delta": [
    {
      "A3130": 1
    },
    {
      "A3132": 1
    },
    {
      "A3455": 0
    }
  ],
  "Total_Delta_Socket": [
    {
      "A3130": 1
    },
    {
      "A3132": 1
    },
    {
      "A3455": 1
    }
  ],
  "Variable_Names": [
    {
      "A3130": []
    },
    {
      "A3132": [
        "o",
        "f",
        "a"
      ]
    },
    {
      "A3455": []
    }
  ]
}
