{
  "Chunk_Type": "T2",
  "Claims": [
    {
      "expr": "Find length(BC) given AB = AC, I incenter of triangle ABC, AI = 3, r = 2",
      "id": "A440_C1",
      "type": "goal"
    },
    {
      "expr": "AB = AC",
      "id": "A440_C2",
      "type": "context"
    },
    {
      "expr": "I is the incenter of triangle ABC",
      "id": "A440_C3",
      "type": "context"
    },
    {
      "expr": "AI = 3",
      "id": "A440_C4",
      "type": "context"
    },
    {
      "expr": "r = 2",
      "id": "A440_C5",
      "type": "context"
    },
    {
      "expr": "X touch point of incircle on AB, Y on BC; IX = IY = r = 2",
      "id": "A440_C6",
      "type": "derived"
    },
    {
      "expr": "IX perpendicular to AB",
      "id": "A440_C7",
      "type": "derived"
    },
    {
      "expr": "IY perpendicular to BC",
      "id": "A440_C8",
      "type": "derived"
    },
    {
      "expr": "triangle AXI is right-angled at X",
      "id": "A440_C9",
      "type": "derived"
    },
    {
      "expr": "AX^2 + IX^2 = AI^2",
      "id": "A440_C10",
      "type": "derived"
    },
    {
      "expr": "AX^2 + 4 = 9",
      "id": "A440_C11",
      "type": "derived"
    },
    {
      "expr": "AX^2 = 5",
      "id": "A440_C12",
      "type": "derived"
    },
    {
      "expr": "AX = sqrt(5)",
      "id": "A440_C13",
      "type": "derived"
    },
    {
      "expr": "angle bisector from A is altitude and median to BC",
      "id": "A440_C14",
      "type": "derived"
    },
    {
      "expr": "I lies on altitude AM from A to BC, M midpoint of BC",
      "id": "A440_C15",
      "type": "derived"
    },
    {
      "expr": "Y is midpoint of BC",
      "id": "A440_C16",
      "type": "derived"
    },
    {
      "expr": "BY = BC / 2",
      "id": "A440_C17",
      "type": "derived"
    },
    {
      "expr": "A, I, Y collinear with I between A and Y",
      "id": "A440_C18",
      "type": "derived"
    },
    {
      "expr": "AY = 5",
      "id": "A440_C19",
      "type": "derived"
    },
    {
      "expr": "triangle AYB is right-angled at Y",
      "id": "A440_C20",
      "type": "derived"
    },
    {
      "expr": "angle at A in triangle AXI = angle at A in triangle AYB",
      "id": "A440_C21",
      "type": "derived"
    },
    {
      "expr": "triangle AXI ~ triangle AYB",
      "id": "A440_C22",
      "type": "derived"
    },
    {
      "expr": "AY / AX = BY / IX",
      "id": "A440_C23",
      "type": "derived"
    },
    {
      "expr": "5 / sqrt(5) = BY / 2",
      "id": "A440_C24",
      "type": "derived"
    },
    {
      "expr": "BY = 2 sqrt(5)",
      "id": "A440_C25",
      "type": "derived"
    },
    {
      "expr": "BC = 4 sqrt(5)",
      "id": "A440_C26",
      "type": "final"
    },
    {
      "expr": "find n in N such that prime( sum_{k=1}^n (-1)^{n-k} k! )",
      "id": "A471_C1",
      "type": "derived"
    },
    {
      "expr": "S(n) = sum_{k=1}^n (-1)^{n-k} k!",
      "id": "A471_C2",
      "type": "context"
    },
    {
      "expr": "S(1) = 1",
      "id": "A471_C3",
      "type": "context"
    },
    {
      "expr": "S(n) = n! - S(n-1) for all n >= 2",
      "id": "A471_C4",
      "type": "derived"
    },
    {
      "expr": "S(2) = 1",
      "id": "A471_C5",
      "type": "derived"
    },
    {
      "expr": "S(3) = 5",
      "id": "A471_C6",
      "type": "derived"
    },
    {
      "expr": "5 is prime",
      "id": "A471_C7",
      "type": "derived"
    },
    {
      "expr": "S(4) = 19",
      "id": "A471_C8",
      "type": "derived"
    },
    {
      "expr": "19 is prime",
      "id": "A471_C9",
      "type": "derived"
    },
    {
      "expr": "S(5) = 101",
      "id": "A471_C10",
      "type": "derived"
    },
    {
      "expr": "101 is prime",
      "id": "A471_C11",
      "type": "derived"
    },
    {
      "expr": "S(6) = 619",
      "id": "A471_C12",
      "type": "derived"
    },
    {
      "expr": "619 is prime",
      "id": "A471_C13",
      "type": "derived"
    },
    {
      "expr": "S(7) = 4421",
      "id": "A471_C14",
      "type": "derived"
    },
    {
      "expr": "4421 is prime",
      "id": "A471_C15",
      "type": "derived"
    },
    {
      "expr": "S(8) = 35899",
      "id": "A471_C16",
      "type": "derived"
    },
    {
      "expr": "35899 is prime",
      "id": "A471_C17",
      "type": "derived"
    },
    {
      "expr": "S(9) = 326981",
      "id": "A471_C18",
      "type": "derived"
    },
    {
      "expr": "S(10) = 3301819",
      "id": "A471_C19",
      "type": "derived"
    },
    {
      "expr": "3301819 is prime",
      "id": "A471_C20",
      "type": "derived"
    },
    {
      "expr": "The n <=160 such that S(n) is prime are: 3,4,5,6,7,8,10,15,19,41,59,61,105,160",
      "id": "A471_C21",
      "type": "final"
    },
    {
      "expr": "find n in N such that prime( sum_{k=1}^n (-(AY - 4))^{n-k} k! )",
      "id": "B12843_C1",
      "type": "goal"
    },
    {
      "expr": "area(PINE) where PI=6, IN=15, NE=6, EP=25, ∠NEP + ∠EPI=60°",
      "id": "A2094_C1",
      "type": "derived"
    },
    {
      "expr": "PI = 6",
      "id": "A2094_C2",
      "type": "context"
    },
    {
      "expr": "IN = 15",
      "id": "A2094_C3",
      "type": "context"
    },
    {
      "expr": "NE = 6",
      "id": "A2094_C4",
      "type": "context"
    },
    {
      "expr": "EP = 25",
      "id": "A2094_C5",
      "type": "context"
    },
    {
      "expr": "∠NEP + ∠EPI = 60°",
      "id": "A2094_C6",
      "type": "context"
    },
    {
      "expr": "Congruent quads P'I'N'E' (E'=P, N'=I) and P''I''N''E'' (P''=E, E''=P', N''=I', I''=N)",
      "id": "A2094_C7",
      "type": "derived"
    },
    {
      "expr": "PP' = 25",
      "id": "A2094_C8",
      "type": "derived"
    },
    {
      "expr": "P'P'' = 25",
      "id": "A2094_C9",
      "type": "derived"
    },
    {
      "expr": "P''P = 25",
      "id": "A2094_C10",
      "type": "derived"
    },
    {
      "expr": "∠I P P' = ∠NEP",
      "id": "A2094_C11",
      "type": "derived"
    },
    {
      "expr": "∠I P P'' = ∠EPI",
      "id": "A2094_C12",
      "type": "derived"
    },
    {
      "expr": "∠P' P P'' = ∠P' P I + ∠I P P''",
      "id": "A2094_C13",
      "type": "derived"
    },
    {
      "expr": "∠P' P P'' = ∠NEP + ∠EPI",
      "id": "A2094_C14",
      "type": "derived"
    },
    {
      "expr": "∠P' P P'' = 60°",
      "id": "A2094_C15",
      "type": "derived"
    },
    {
      "expr": "∠P P' P'' = 60°",
      "id": "A2094_C16",
      "type": "derived"
    },
    {
      "expr": "∠P P'' P' = 60°",
      "id": "A2094_C17",
      "type": "derived"
    },
    {
      "expr": "△PP'P'' has sides 25, 25, 25",
      "id": "A2094_C18",
      "type": "derived"
    },
    {
      "expr": "△PP'P'' equilateral side 25",
      "id": "A2094_C19",
      "type": "derived"
    },
    {
      "expr": "N I = 15",
      "id": "A2094_C20",
      "type": "derived"
    },
    {
      "expr": "I I' = 15",
      "id": "A2094_C21",
      "type": "derived"
    },
    {
      "expr": "I' N = 15",
      "id": "A2094_C22",
      "type": "derived"
    },
    {
      "expr": "△N I I' has sides 15, 15, 15",
      "id": "A2094_C23",
      "type": "derived"
    },
    {
      "expr": "△N I I' equilateral side 15",
      "id": "A2094_C24",
      "type": "derived"
    },
    {
      "expr": "area(△PP'P'') = (25^2 sqrt(3))/4",
      "id": "A2094_C25",
      "type": "derived"
    },
    {
      "expr": "area(△N I I') = (15^2 sqrt(3))/4",
      "id": "A2094_C26",
      "type": "derived"
    },
    {
      "expr": "area(△PP'P'') - area(△N I I') = 100 sqrt(3)",
      "id": "A2094_C27",
      "type": "derived"
    },
    {
      "expr": "Three quads fill area(△PP'P'') - area(△N I I')",
      "id": "A2094_C28",
      "type": "derived"
    },
    {
      "expr": "area(PINE) + area(P'I'N'E') + area(P''I''N''E'') = 100 sqrt(3)",
      "id": "A2094_C29",
      "type": "derived"
    },
    {
      "expr": "area(P'I'N'E') = area(PINE)",
      "id": "A2094_C30",
      "type": "derived"
    },
    {
      "expr": "area(P''I''N''E'') = area(PINE)",
      "id": "A2094_C31",
      "type": "derived"
    },
    {
      "expr": "3 * area(PINE) = 100 sqrt(3)",
      "id": "A2094_C32",
      "type": "derived"
    },
    {
      "expr": "area(PINE) = 100 sqrt(3)/3",
      "id": "A2094_C33",
      "type": "final"
    },
    {
      "expr": "area(PINE) where PI=(S(10) - 3301813), IN=15, NE=(S(10) - 3301813), EP=25, ∠NEP + ∠EPI=60°",
      "id": "B3276_C1",
      "type": "goal"
    }
  ],
  "Class_ID": [
    "B12843",
    "B3276"
  ],
  "Connecting_Point": [
    {
      "B12843": {
        "1": "(AY - 4)"
      }
    },
    {
      "B3276": {
        "6": "(S(10) - 3301813)"
      }
    }
  ],
  "Delta_Depth": [
    {
      "A440": {
        "AY": 19
      }
    },
    {
      "A471": {
        "S(10)": 19
      }
    },
    {
      "A2094": 0
    }
  ],
  "Delta_Factor": [
    {
      "A440": 0.73
    },
    {
      "A471": 0.9
    },
    {
      "A2094": 0
    }
  ],
  "Delta_Socket": [
    {
      "A440": {
        "3": 3.0
      }
    },
    {
      "A471": {
        "1": 1.0
      }
    },
    {
      "A2094": {
        "6": 6.0
      }
    }
  ],
  "Delta_Socket_Order": [
    {
      "A440": 1
    },
    {
      "A471": 1
    },
    {
      "A2094": 1
    }
  ],
  "Delta_Source": [
    {
      "A440": "derived"
    },
    {
      "A471": "derived"
    },
    {
      "A2094": ""
    }
  ],
  "Delta_Value": [
    {
      "A440": {
        "AY": "5"
      }
    },
    {
      "A471": {
        "S(10)": "3301819"
      }
    },
    {
      "A2094": {}
    }
  ],
  "Delta_Value_Order": [
    {
      "A440": 1
    },
    {
      "A471": 9
    },
    {
      "A2094": 0
    }
  ],
  "Delta_Variable_Names": [
    {
      "A440": [
        "AY"
      ]
    },
    {
      "A471": [
        "S"
      ]
    },
    {
      "A2094": []
    }
  ],
  "Ground_Truth": [
    {
      "A440": "4\\sqrt{5}"
    },
    {
      "A471": "3, 4, 5, 6, 7, 8, 10, 15, 19, 41, 59, 61, 105, 160"
    },
    {
      "A2094": "\\frac{100 \\sqrt{3}}{3}"
    }
  ],
  "Math_Problem": "Let $A B C$ be an isosceles triangle with apex $A$. Let $I$ be the incenter. If $A I=3$ and the distance from $I$ to $B C$ is 2 , then what is the length of $B C$ ? Instead of determining the length of the base $BC$, simply find $d = AY - 4$, where $AY$ is the length of the segment from $A$ to $Y$ along the angle bisector, and $Y$ is the point of tangency of the incircle with $BC$. Find an $n$ such that $n! + (-d)(n-1)! + (-d)^2 (n-2)! + (-d)^3 (n-3)! + \\cdots + (-d)^{n-1} \\cdot 1!$ is prime. Be prepared to justify your answer for $\\left\\{\\begin{array}{c}n, \\\\\\\\ \\left[\\frac{n+225}{10}\\right],\\\\ \\end{array} n \\leq 25\\right.$ points, where $[N]$ is the greatest integer less than $N$. Instead of finding a natural number $n$ such that the given alternating sum of factorials is prime, simply find $d = S(10) - 3301813$, where $S(10)$ is the value of that alternating sum when the largest factorial term is $10!$. For dinner, Priya is eating grilled pineapple spears. Each spear is in the shape of the quadrilateral PINE, with $P I=d \\mathrm{~cm}$, $I N=15 \\mathrm{~cm}$, $N E=d \\mathrm{~cm}$, $E P=25 \\mathrm{~cm}$, and $\\angle N E P+\\angle E P I=60^{\\circ}$. What is the area of each spear, in $\\mathrm{cm}^{2}$ ?",
  "Max_Delta_Depth": [
    {
      "A440": 19
    },
    {
      "A471": 19
    },
    {
      "A2094": 0
    }
  ],
  "Max_Delta_Factor": [
    {
      "A440": 0.73
    },
    {
      "A471": 0.9
    },
    {
      "A2094": 0
    }
  ],
  "Min_Delta_Depth": [
    {
      "A440": 19
    },
    {
      "A471": 5
    },
    {
      "A2094": 0
    }
  ],
  "Min_Delta_Factor": [
    {
      "A440": 0.73
    },
    {
      "A471": 0.24
    },
    {
      "A2094": 0
    }
  ],
  "Multiple_Synthesis_Class": "MP3",
  "Predicted_Answer": [
    {
      "A440": "4\\sqrt{5}"
    },
    {
      "A471": "3, 4, 5, 6, 7, 8, 10, 15, 19, 41, 59, 61, 105, 160"
    },
    {
      "A2094": "100 sqrt(3)/3"
    }
  ],
  "Problem_ID": 58,
  "Problem_Length": [
    {
      "A440": 164
    },
    {
      "A471": 262
    },
    {
      "A2094": 293
    }
  ],
  "Problem_Level": [
    {
      "A440": "KbsdJames_Omni-MATH_3.5"
    },
    {
      "A471": "KbsdJames_Omni-MATH_3.5"
    },
    {
      "A2094": "KbsdJames_Omni-MATH_4.0"
    }
  ],
  "Problem_Source": [
    {
      "A440": "HMMT_2"
    },
    {
      "A471": "HMMT_2"
    },
    {
      "A2094": "HMMT_11"
    }
  ],
  "Problem_Type": [
    {
      "A440": [
        "Mathematics -> Geometry -> Plane Geometry -> Triangulations"
      ]
    },
    {
      "A471": [
        "Mathematics -> Number Theory -> Factorization"
      ]
    },
    {
      "A2094": [
        "Mathematics -> Geometry -> Plane Geometry -> Polygons"
      ]
    }
  ],
  "Source_Delta_Socket": [
    {
      "A440": "goal"
    },
    {
      "A471": "goal"
    },
    {
      "A2094": "goal"
    }
  ],
  "Steps": [
    {
      "conclusions": [
        "A440_C2: AB = AC",
        "A440_C3: I is the incenter of triangle ABC",
        "A440_C4: AI = 3",
        "A440_C5: r = 2"
      ],
      "id": "A440_S1",
      "premises": [
        "A440_C1: Find length(BC) given AB = AC, I incenter of triangle ABC, AI = 3, r = 2"
      ],
      "rule": "problem setup"
    },
    {
      "conclusions": [
        "A440_C6: X touch point of incircle on AB, Y on BC; IX = IY = r = 2"
      ],
      "id": "A440_S2",
      "premises": [
        "A440_C3: I is the incenter of triangle ABC",
        "A440_C5: r = 2"
      ],
      "rule": "incircle touch points and radii"
    },
    {
      "conclusions": [
        "A440_C7: IX perpendicular to AB"
      ],
      "id": "A440_S3",
      "premises": [
        "A440_C6: X touch point of incircle on AB, Y on BC; IX = IY = r = 2"
      ],
      "rule": "radius perpendicular to tangent"
    },
    {
      "conclusions": [
        "A440_C8: IY perpendicular to BC"
      ],
      "id": "A440_S4",
      "premises": [
        "A440_C6: X touch point of incircle on AB, Y on BC; IX = IY = r = 2"
      ],
      "rule": "radius perpendicular to tangent"
    },
    {
      "conclusions": [
        "A440_C9: triangle AXI is right-angled at X"
      ],
      "id": "A440_S5",
      "premises": [
        "A440_C7: IX perpendicular to AB"
      ],
      "rule": "right angle from perpendicular"
    },
    {
      "conclusions": [
        "A440_C10: AX^2 + IX^2 = AI^2"
      ],
      "id": "A440_S6",
      "premises": [
        "A440_C9: triangle AXI is right-angled at X"
      ],
      "rule": "Pythagorean theorem"
    },
    {
      "conclusions": [
        "A440_C11: AX^2 + 4 = 9"
      ],
      "id": "A440_S7",
      "premises": [
        "A440_C10: AX^2 + IX^2 = AI^2",
        "A440_C4: AI = 3",
        "A440_C6: X touch point of incircle on AB, Y on BC; IX = IY = r = 2"
      ],
      "rule": "substitution of known lengths"
    },
    {
      "conclusions": [
        "A440_C12: AX^2 = 5"
      ],
      "id": "A440_S8",
      "premises": [
        "A440_C11: AX^2 + 4 = 9"
      ],
      "rule": "algebraic simplification"
    },
    {
      "conclusions": [
        "A440_C13: AX = sqrt(5)"
      ],
      "id": "A440_S9",
      "premises": [
        "A440_C12: AX^2 = 5"
      ],
      "rule": "positive square root for length"
    },
    {
      "conclusions": [
        "A440_C14: angle bisector from A is altitude and median to BC"
      ],
      "id": "A440_S10",
      "premises": [
        "A440_C2: AB = AC"
      ],
      "rule": "properties of isosceles triangle"
    },
    {
      "conclusions": [
        "A440_C15: I lies on altitude AM from A to BC, M midpoint of BC"
      ],
      "id": "A440_S11",
      "premises": [
        "A440_C3: I is the incenter of triangle ABC",
        "A440_C14: angle bisector from A is altitude and median to BC"
      ],
      "rule": "incenter on angle bisector"
    },
    {
      "conclusions": [
        "A440_C16: Y is midpoint of BC"
      ],
      "id": "A440_S12",
      "premises": [
        "A440_C2: AB = AC",
        "A440_C3: I is the incenter of triangle ABC"
      ],
      "rule": "symmetry in isosceles triangle"
    },
    {
      "conclusions": [
        "A440_C17: BY = BC / 2"
      ],
      "id": "A440_S13",
      "premises": [
        "A440_C16: Y is midpoint of BC"
      ],
      "rule": "midpoint definition"
    },
    {
      "conclusions": [
        "A440_C18: A, I, Y collinear with I between A and Y"
      ],
      "id": "A440_S14",
      "premises": [
        "A440_C15: I lies on altitude AM from A to BC, M midpoint of BC",
        "A440_C16: Y is midpoint of BC"
      ],
      "rule": "collinearity on altitude"
    },
    {
      "conclusions": [
        "A440_C19: AY = 5"
      ],
      "id": "A440_S15",
      "premises": [
        "A440_C18: A, I, Y collinear with I between A and Y",
        "A440_C4: AI = 3",
        "A440_C6: X touch point of incircle on AB, Y on BC; IX = IY = r = 2"
      ],
      "rule": "addition of segments"
    },
    {
      "conclusions": [
        "A440_C20: triangle AYB is right-angled at Y"
      ],
      "id": "A440_S16",
      "premises": [
        "A440_C14: angle bisector from A is altitude and median to BC",
        "A440_C8: IY perpendicular to BC"
      ],
      "rule": "altitude perpendicular to base"
    },
    {
      "conclusions": [
        "A440_C21: angle at A in triangle AXI = angle at A in triangle AYB"
      ],
      "id": "A440_S17",
      "premises": [
        "A440_C15: I lies on altitude AM from A to BC, M midpoint of BC",
        "A440_C18: A, I, Y collinear with I between A and Y"
      ],
      "rule": "common angle from bisector alignment"
    },
    {
      "conclusions": [
        "A440_C22: triangle AXI ~ triangle AYB"
      ],
      "id": "A440_S18",
      "premises": [
        "A440_C9: triangle AXI is right-angled at X",
        "A440_C20: triangle AYB is right-angled at Y",
        "A440_C21: angle at A in triangle AXI = angle at A in triangle AYB"
      ],
      "rule": "AA similarity criterion"
    },
    {
      "conclusions": [
        "A440_C23: AY / AX = BY / IX"
      ],
      "id": "A440_S19",
      "premises": [
        "A440_C22: triangle AXI ~ triangle AYB"
      ],
      "rule": "corresponding sides in similar triangles"
    },
    {
      "conclusions": [
        "A440_C24: 5 / sqrt(5) = BY / 2"
      ],
      "id": "A440_S20",
      "premises": [
        "A440_C23: AY / AX = BY / IX",
        "A440_C19: AY = 5",
        "A440_C13: AX = sqrt(5)",
        "A440_C6: X touch point of incircle on AB, Y on BC; IX = IY = r = 2"
      ],
      "rule": "substitution in similarity ratio"
    },
    {
      "conclusions": [
        "A440_C25: BY = 2 sqrt(5)"
      ],
      "id": "A440_S21",
      "premises": [
        "A440_C24: 5 / sqrt(5) = BY / 2"
      ],
      "rule": "solve for BY"
    },
    {
      "conclusions": [
        "A440_C26: BC = 4 sqrt(5)"
      ],
      "id": "A440_S22",
      "premises": [
        "A440_C17: BY = BC / 2",
        "A440_C25: BY = 2 sqrt(5)"
      ],
      "rule": "double the half-length"
    },
    {
      "conclusions": [
        "A471_C2: S(n) = sum_{k=1}^n (-1)^{n-k} k!",
        "A471_C3: S(1) = 1"
      ],
      "id": "A471_S1",
      "premises": [
        "A471_C1: find n in N such that prime( sum_{k=1}^n (-1)^{n-k} k! )"
      ],
      "rule": "problem setup"
    },
    {
      "conclusions": [
        "A471_C4: S(n) = n! - S(n-1) for all n >= 2"
      ],
      "id": "A471_S2",
      "premises": [
        "A471_C2: S(n) = sum_{k=1}^n (-1)^{n-k} k!"
      ],
      "rule": "recurrence derivation from definition"
    },
    {
      "conclusions": [
        "A471_C5: S(2) = 1"
      ],
      "id": "A471_S3",
      "premises": [
        "A471_C4: S(n) = n! - S(n-1) for all n >= 2",
        "A471_C3: S(1) = 1"
      ],
      "rule": "recurrence application"
    },
    {
      "conclusions": [
        "A471_C6: S(3) = 5"
      ],
      "id": "A471_S4",
      "premises": [
        "A471_C4: S(n) = n! - S(n-1) for all n >= 2",
        "A471_C5: S(2) = 1"
      ],
      "rule": "recurrence application"
    },
    {
      "conclusions": [
        "A471_C7: 5 is prime"
      ],
      "id": "A471_S5",
      "premises": [
        "A471_C6: S(3) = 5"
      ],
      "rule": "primality verification"
    },
    {
      "conclusions": [
        "A471_C8: S(4) = 19"
      ],
      "id": "A471_S6",
      "premises": [
        "A471_C4: S(n) = n! - S(n-1) for all n >= 2",
        "A471_C6: S(3) = 5"
      ],
      "rule": "recurrence application"
    },
    {
      "conclusions": [
        "A471_C9: 19 is prime"
      ],
      "id": "A471_S7",
      "premises": [
        "A471_C8: S(4) = 19"
      ],
      "rule": "primality verification"
    },
    {
      "conclusions": [
        "A471_C10: S(5) = 101"
      ],
      "id": "A471_S8",
      "premises": [
        "A471_C4: S(n) = n! - S(n-1) for all n >= 2",
        "A471_C8: S(4) = 19"
      ],
      "rule": "recurrence application"
    },
    {
      "conclusions": [
        "A471_C11: 101 is prime"
      ],
      "id": "A471_S9",
      "premises": [
        "A471_C10: S(5) = 101"
      ],
      "rule": "primality verification"
    },
    {
      "conclusions": [
        "A471_C12: S(6) = 619"
      ],
      "id": "A471_S10",
      "premises": [
        "A471_C4: S(n) = n! - S(n-1) for all n >= 2",
        "A471_C10: S(5) = 101"
      ],
      "rule": "recurrence application"
    },
    {
      "conclusions": [
        "A471_C13: 619 is prime"
      ],
      "id": "A471_S11",
      "premises": [
        "A471_C12: S(6) = 619"
      ],
      "rule": "primality verification"
    },
    {
      "conclusions": [
        "A471_C14: S(7) = 4421"
      ],
      "id": "A471_S12",
      "premises": [
        "A471_C4: S(n) = n! - S(n-1) for all n >= 2",
        "A471_C12: S(6) = 619"
      ],
      "rule": "recurrence application"
    },
    {
      "conclusions": [
        "A471_C15: 4421 is prime"
      ],
      "id": "A471_S13",
      "premises": [
        "A471_C14: S(7) = 4421"
      ],
      "rule": "primality verification"
    },
    {
      "conclusions": [
        "A471_C16: S(8) = 35899"
      ],
      "id": "A471_S14",
      "premises": [
        "A471_C4: S(n) = n! - S(n-1) for all n >= 2",
        "A471_C14: S(7) = 4421"
      ],
      "rule": "recurrence application"
    },
    {
      "conclusions": [
        "A471_C17: 35899 is prime"
      ],
      "id": "A471_S15",
      "premises": [
        "A471_C16: S(8) = 35899"
      ],
      "rule": "primality verification"
    },
    {
      "conclusions": [
        "A471_C18: S(9) = 326981"
      ],
      "id": "A471_S16",
      "premises": [
        "A471_C4: S(n) = n! - S(n-1) for all n >= 2",
        "A471_C16: S(8) = 35899"
      ],
      "rule": "recurrence application"
    },
    {
      "conclusions": [
        "A471_C19: S(10) = 3301819"
      ],
      "id": "A471_S17",
      "premises": [
        "A471_C4: S(n) = n! - S(n-1) for all n >= 2",
        "A471_C18: S(9) = 326981"
      ],
      "rule": "recurrence application"
    },
    {
      "conclusions": [
        "A471_C20: 3301819 is prime"
      ],
      "id": "A471_S18",
      "premises": [
        "A471_C19: S(10) = 3301819"
      ],
      "rule": "primality verification"
    },
    {
      "conclusions": [
        "A471_C21: The n <=160 such that S(n) is prime are: 3,4,5,6,7,8,10,15,19,41,59,61,105,160"
      ],
      "id": "A471_S19",
      "premises": [
        "A471_C4: S(n) = n! - S(n-1) for all n >= 2",
        "A471_C20: 3301819 is prime"
      ],
      "rule": "extended numerical computation and primality testing"
    },
    {
      "conclusions": [
        "A471_C1: find n in N such that prime( sum_{k=1}^n (-1)^{n-k} k! )"
      ],
      "id": "B12843_S1",
      "premises": [
        "B12843_C1: find n in N such that prime( sum_{k=1}^n (-(AY - 4))^{n-k} k! )",
        "A440_C19: AY = 5"
      ],
      "rule": "problem connection"
    },
    {
      "conclusions": [
        "A2094_C2: PI = 6",
        "A2094_C3: IN = 15",
        "A2094_C4: NE = 6",
        "A2094_C5: EP = 25",
        "A2094_C6: ∠NEP + ∠EPI = 60°"
      ],
      "id": "A2094_S1",
      "premises": [
        "A2094_C1: area(PINE) where PI=6, IN=15, NE=6, EP=25, ∠NEP + ∠EPI=60°"
      ],
      "rule": "problem setup"
    },
    {
      "conclusions": [
        "A2094_C7: Congruent quads P'I'N'E' (E'=P, N'=I) and P''I''N''E'' (P''=E, E''=P', N''=I', I''=N)"
      ],
      "id": "A2094_S2",
      "premises": [
        "A2094_C2: PI = 6",
        "A2094_C3: IN = 15",
        "A2094_C4: NE = 6",
        "A2094_C5: EP = 25",
        "A2094_C6: ∠NEP + ∠EPI = 60°"
      ],
      "rule": "geometric construction"
    },
    {
      "conclusions": [
        "A2094_C8: PP' = 25"
      ],
      "id": "A2094_S3",
      "premises": [
        "A2094_C7: Congruent quads P'I'N'E' (E'=P, N'=I) and P''I''N''E'' (P''=E, E''=P', N''=I', I''=N)",
        "A2094_C5: EP = 25"
      ],
      "rule": "side identification"
    },
    {
      "conclusions": [
        "A2094_C9: P'P'' = 25"
      ],
      "id": "A2094_S4",
      "premises": [
        "A2094_C7: Congruent quads P'I'N'E' (E'=P, N'=I) and P''I''N''E'' (P''=E, E''=P', N''=I', I''=N)",
        "A2094_C5: EP = 25"
      ],
      "rule": "side identification"
    },
    {
      "conclusions": [
        "A2094_C10: P''P = 25"
      ],
      "id": "A2094_S5",
      "premises": [
        "A2094_C7: Congruent quads P'I'N'E' (E'=P, N'=I) and P''I''N''E'' (P''=E, E''=P', N''=I', I''=N)",
        "A2094_C5: EP = 25"
      ],
      "rule": "side identification"
    },
    {
      "conclusions": [
        "A2094_C11: ∠I P P' = ∠NEP"
      ],
      "id": "A2094_S6",
      "premises": [
        "A2094_C7: Congruent quads P'I'N'E' (E'=P, N'=I) and P''I''N''E'' (P''=E, E''=P', N''=I', I''=N)"
      ],
      "rule": "congruence angle mapping"
    },
    {
      "conclusions": [
        "A2094_C12: ∠I P P'' = ∠EPI"
      ],
      "id": "A2094_S7",
      "premises": [
        "A2094_C7: Congruent quads P'I'N'E' (E'=P, N'=I) and P''I''N''E'' (P''=E, E''=P', N''=I', I''=N)"
      ],
      "rule": "angle identification"
    },
    {
      "conclusions": [
        "A2094_C13: ∠P' P P'' = ∠P' P I + ∠I P P''"
      ],
      "id": "A2094_S8",
      "premises": [
        "A2094_C7: Congruent quads P'I'N'E' (E'=P, N'=I) and P''I''N''E'' (P''=E, E''=P', N''=I', I''=N)"
      ],
      "rule": "adjacent angles"
    },
    {
      "conclusions": [
        "A2094_C14: ∠P' P P'' = ∠NEP + ∠EPI"
      ],
      "id": "A2094_S9",
      "premises": [
        "A2094_C13: ∠P' P P'' = ∠P' P I + ∠I P P''",
        "A2094_C11: ∠I P P' = ∠NEP",
        "A2094_C12: ∠I P P'' = ∠EPI"
      ],
      "rule": "angle addition"
    },
    {
      "conclusions": [
        "A2094_C15: ∠P' P P'' = 60°"
      ],
      "id": "A2094_S10",
      "premises": [
        "A2094_C14: ∠P' P P'' = ∠NEP + ∠EPI",
        "A2094_C6: ∠NEP + ∠EPI = 60°"
      ],
      "rule": "given sum"
    },
    {
      "conclusions": [
        "A2094_C16: ∠P P' P'' = 60°",
        "A2094_C17: ∠P P'' P' = 60°"
      ],
      "id": "A2094_S11",
      "premises": [
        "A2094_C7: Congruent quads P'I'N'E' (E'=P, N'=I) and P''I''N''E'' (P''=E, E''=P', N''=I', I''=N)",
        "A2094_C15: ∠P' P P'' = 60°"
      ],
      "rule": "construction symmetry"
    },
    {
      "conclusions": [
        "A2094_C18: △PP'P'' has sides 25, 25, 25"
      ],
      "id": "A2094_S12",
      "premises": [
        "A2094_C8: PP' = 25",
        "A2094_C9: P'P'' = 25",
        "A2094_C10: P''P = 25"
      ],
      "rule": "equal sides"
    },
    {
      "conclusions": [
        "A2094_C19: △PP'P'' equilateral side 25"
      ],
      "id": "A2094_S13",
      "premises": [
        "A2094_C18: △PP'P'' has sides 25, 25, 25",
        "A2094_C15: ∠P' P P'' = 60°",
        "A2094_C16: ∠P P' P'' = 60°",
        "A2094_C17: ∠P P'' P' = 60°"
      ],
      "rule": "equilateral characterization"
    },
    {
      "conclusions": [
        "A2094_C20: N I = 15"
      ],
      "id": "A2094_S14",
      "premises": [
        "A2094_C7: Congruent quads P'I'N'E' (E'=P, N'=I) and P''I''N''E'' (P''=E, E''=P', N''=I', I''=N)",
        "A2094_C3: IN = 15"
      ],
      "rule": "inner side"
    },
    {
      "conclusions": [
        "A2094_C21: I I' = 15"
      ],
      "id": "A2094_S15",
      "premises": [
        "A2094_C7: Congruent quads P'I'N'E' (E'=P, N'=I) and P''I''N''E'' (P''=E, E''=P', N''=I', I''=N)",
        "A2094_C3: IN = 15"
      ],
      "rule": "inner side"
    },
    {
      "conclusions": [
        "A2094_C22: I' N = 15"
      ],
      "id": "A2094_S16",
      "premises": [
        "A2094_C7: Congruent quads P'I'N'E' (E'=P, N'=I) and P''I''N''E'' (P''=E, E''=P', N''=I', I''=N)",
        "A2094_C3: IN = 15"
      ],
      "rule": "inner side"
    },
    {
      "conclusions": [
        "A2094_C23: △N I I' has sides 15, 15, 15"
      ],
      "id": "A2094_S17",
      "premises": [
        "A2094_C20: N I = 15",
        "A2094_C21: I I' = 15",
        "A2094_C22: I' N = 15"
      ],
      "rule": "equal inner sides"
    },
    {
      "conclusions": [
        "A2094_C24: △N I I' equilateral side 15"
      ],
      "id": "A2094_S18",
      "premises": [
        "A2094_C7: Congruent quads P'I'N'E' (E'=P, N'=I) and P''I''N''E'' (P''=E, E''=P', N''=I', I''=N)",
        "A2094_C23: △N I I' has sides 15, 15, 15"
      ],
      "rule": "inner equilateral"
    },
    {
      "conclusions": [
        "A2094_C25: area(△PP'P'') = (25^2 sqrt(3))/4"
      ],
      "id": "A2094_S19",
      "premises": [
        "A2094_C19: △PP'P'' equilateral side 25"
      ],
      "rule": "equilateral area formula"
    },
    {
      "conclusions": [
        "A2094_C26: area(△N I I') = (15^2 sqrt(3))/4"
      ],
      "id": "A2094_S20",
      "premises": [
        "A2094_C24: △N I I' equilateral side 15"
      ],
      "rule": "equilateral area formula"
    },
    {
      "conclusions": [
        "A2094_C27: area(△PP'P'') - area(△N I I') = 100 sqrt(3)"
      ],
      "id": "A2094_S21",
      "premises": [
        "A2094_C25: area(△PP'P'') = (25^2 sqrt(3))/4",
        "A2094_C26: area(△N I I') = (15^2 sqrt(3))/4"
      ],
      "rule": "area subtraction"
    },
    {
      "conclusions": [
        "A2094_C28: Three quads fill area(△PP'P'') - area(△N I I')"
      ],
      "id": "A2094_S22",
      "premises": [
        "A2094_C7: Congruent quads P'I'N'E' (E'=P, N'=I) and P''I''N''E'' (P''=E, E''=P', N''=I', I''=N)"
      ],
      "rule": "configuration filling"
    },
    {
      "conclusions": [
        "A2094_C29: area(PINE) + area(P'I'N'E') + area(P''I''N''E'') = 100 sqrt(3)"
      ],
      "id": "A2094_S23",
      "premises": [
        "A2094_C28: Three quads fill area(△PP'P'') - area(△N I I')",
        "A2094_C27: area(△PP'P'') - area(△N I I') = 100 sqrt(3)"
      ],
      "rule": "total quad area"
    },
    {
      "conclusions": [
        "A2094_C30: area(P'I'N'E') = area(PINE)",
        "A2094_C31: area(P''I''N''E'') = area(PINE)"
      ],
      "id": "A2094_S24",
      "premises": [
        "A2094_C7: Congruent quads P'I'N'E' (E'=P, N'=I) and P''I''N''E'' (P''=E, E''=P', N''=I', I''=N)"
      ],
      "rule": "congruent areas"
    },
    {
      "conclusions": [
        "A2094_C32: 3 * area(PINE) = 100 sqrt(3)"
      ],
      "id": "A2094_S25",
      "premises": [
        "A2094_C29: area(PINE) + area(P'I'N'E') + area(P''I''N''E'') = 100 sqrt(3)",
        "A2094_C30: area(P'I'N'E') = area(PINE)",
        "A2094_C31: area(P''I''N''E'') = area(PINE)"
      ],
      "rule": "equal areas sum"
    },
    {
      "conclusions": [
        "A2094_C33: area(PINE) = 100 sqrt(3)/3"
      ],
      "id": "A2094_S26",
      "premises": [
        "A2094_C32: 3 * area(PINE) = 100 sqrt(3)"
      ],
      "rule": "division by 3"
    },
    {
      "conclusions": [
        "A2094_C1: area(PINE) where PI=6, IN=15, NE=6, EP=25, ∠NEP + ∠EPI=60°"
      ],
      "id": "B3276_S1",
      "premises": [
        "B3276_C1: area(PINE) where PI=(S(10) - 3301813), IN=15, NE=(S(10) - 3301813), EP=25, ∠NEP + ∠EPI=60°",
        "A471_C19: S(10) = 3301819"
      ],
      "rule": "problem connection"
    }
  ],
  "Sub_Class_ID": [
    {
      "A440": "A440_DG_1"
    },
    {
      "A471": "A471_DG_9"
    },
    {
      "A2094": "A2094_OG_1"
    }
  ],
  "Synthesised_By": [
    {
      "A440": "Let $A B C$ be an isosceles triangle with apex $A$. Let $I$ be the incenter. If $A I=3$ and the distance from $I$ to $B C$ is 2 , then what is the length of $B C$ ?"
    },
    {
      "A471": "Find an $n$ such that $n!-(n-1)!+(n-2)!-(n-3)!+\\cdots \\pm 1$ ! is prime. Be prepared to justify your answer for $\\left\\{\\begin{array}{c}n, \\\\ {\\left[\\frac{n+225}{10}\\right],}\\end{array} n \\leq 25\\right.$ points, where $[N]$ is the greatest integer less than $N$."
    },
    {
      "A2094": "For dinner, Priya is eating grilled pineapple spears. Each spear is in the shape of the quadrilateral PINE, with $P I=6 \\mathrm{~cm}, I N=15 \\mathrm{~cm}, N E=6 \\mathrm{~cm}, E P=25 \\mathrm{~cm}$, and \\angle N E P+\\angle E P I=60^{\\circ}$. What is the area of each spear, in \\mathrm{cm}^{2}$ ?"
    }
  ],
  "Synthesised_Problem_Length": 1220,
  "Synthesised_Status": "Stop",
  "Total_Claims": [
    {
      "A440": 26
    },
    {
      "A471": 21
    },
    {
      "A2094": 33
    }
  ],
  "Total_Delta": [
    {
      "A440": 1
    },
    {
      "A471": 9
    },
    {
      "A2094": 0
    }
  ],
  "Total_Delta_Socket": [
    {
      "A440": 1
    },
    {
      "A471": 1
    },
    {
      "A2094": 1
    }
  ],
  "Variable_Names": [
    {
      "A440": [
        "C",
        "B",
        "A",
        "I"
      ]
    },
    {
      "A471": [
        "n",
        "c",
        "N"
      ]
    },
    {
      "A2094": [
        "P",
        "I",
        "N",
        "E"
      ]
    }
  ]
}
