{
  "Problem_ID": 42,
  "Chunk_Type": "T4",
  "Class_ID": "B8479",
  "Multiple_Synthesis_Class": "MP2",
  "Sub_Class_ID": [
    {
      "A4395": "A4395_DG_1"
    },
    {
      "A4402": "A4402_DG_2"
    }
  ],
  "Synthesis_Trace": "DG-DG",
  "Synthesis_Status": "Continuable",
  "Math_Problem": "Solve the equation \\[(a^{2},b^{2})+(a,bc)+(b,ac)+(c,ab)=199.\\] in positive integers. (Here $(x,y)$ denotes the greatest common divisor of $x$ and $y$.) Instead of determining the positive integers satisfying the given equation on greatest common divisors, simply find $m = c - 476$, where $c$ is the positive integer appearing in the term $(c, ab)$. Let $n$ be a given positive integer. Solve the system \\[x_1 + x_2^2 + x_3^3 + \\cdots + x_n^n = n,\\] \\[x_1 + 2x_2 + 3x_3 + \\cdots + n x_n = \\frac{n(n+m)}{(m+1)}\\]\nin the set of nonnegative real numbers.",
  "Connecting_Sentence": [
    {
      "A4395": "Instead of determining the positive integers satisfying the given equation on greatest common divisors, simply find $m = c - 476$, where $c$ is the positive integer appearing in the term $(c, ab)$."
    },
    {
      "A4402": "None"
    }
  ],
  "Synthesised_By": [
    {
      "A4395": "Solve the equation \n\\[(a^{2},b^{2})+(a,bc)+(b,ac)+(c,ab)=199.\\]\nin positive integers. \n(Here $(x,y)$ denotes the greatest common divisor of $x$ and $y$.) Instead of determining the positive integers satisfying the given equation on greatest common divisors, simply find $m = c - 476$, where $c$ is the positive integer appearing in the term $(c, ab)$."
    },
    {
      "A4402": "Let $n$ be a given positive integer. Solve the system \n\\[x_1 + x_2^2 + x_3^3 + \\cdots + x_n^n = n,\\]\n\\[x_1 + 2x_2 + 3x_3 + \\cdots + nx_n = \\frac{n(n+1)}{2}\\]\nin the set of nonnegative real numbers."
    }
  ],
  "Original_Problem": [
    {
      "A4395": "Solve the equation \n\\[(a^{2},b^{2})+(a,bc)+(b,ac)+(c,ab)=199.\\]\nin positive integers. \n(Here $(x,y)$ denotes the greatest common divisor of $x$ and $y$.)"
    },
    {
      "A4402": "Let $n$ be a given positive integer. Solve the system \n\\[x_1 + x_2^2 + x_3^3 + \\cdots + x_n^n = n,\\]\n\\[x_1 + 2x_2 + 3x_3 + \\cdots + nx_n = \\frac{n(n+1)}{2}\\]\nin the set of nonnegative real numbers."
    }
  ],
  "Problem_Type": [
    {
      "A4395": [
        "Mathematics -> Number Theory -> Greatest Common Divisors (GCD)",
        "Mathematics -> Algebra -> Algebra -> Equations and Inequalities"
      ]
    },
    {
      "A4402": [
        "Mathematics -> Algebra -> Algebra -> Algebraic Expressions"
      ]
    }
  ],
  "Problem_Level": [
    {
      "A4395": "KbsdJames_Omni-MATH_6.5"
    },
    {
      "A4402": "KbsdJames_Omni-MATH_6.5"
    }
  ],
  "Problem_Source": [
    {
      "A4395": "tuymaada_olympiad"
    },
    {
      "A4402": "czech-polish-slovak matches"
    }
  ],
  "Problem_Length": [
    {
      "A4395": 153
    },
    {
      "A4402": 197
    }
  ],
  "Synthesised_Problem_Length": 578,
  "Ground_Truth": [
    {
      "A4395": "(a, b, c) = (238,238,477)"
    },
    {
      "A4402": "(x_1, x_2, \\ldots, x_n) = (1, 1, \\ldots, 1)"
    }
  ],
  "Predicted_Answer": [
    {
      "A4395": "(238, 238, 477)"
    },
    {
      "A4402": "(1, 1, \\ldots, 1)"
    }
  ],
  "Connecting_Point": [
    {
      "B8479": {
        "1": "(c - 476)"
      }
    }
  ],
  "Delta_Factor": [
    {
      "A4395": 0.91
    },
    {
      "A4402": 0.96
    }
  ],
  "Delta_Value": [
    {
      "A4395": {
        "c": "477"
      }
    },
    {
      "A4402": {
        "x_1": "1"
      }
    }
  ],
  "Delta_Depth": [
    {
      "A4395": {
        "c": 10
      }
    },
    {
      "A4402": {
        "x_1": 25
      }
    }
  ],
  "Delta_Source": [
    {
      "A4395": "derived"
    },
    {
      "A4402": "derived"
    }
  ],
  "Delta_Value_Order": [
    {
      "A4395": 1
    },
    {
      "A4402": 2
    }
  ],
  "Delta_Variable_Names": [
    {
      "A4395": [
        "c"
      ]
    },
    {
      "A4402": [
        "x"
      ]
    }
  ],
  "Delta_Socket": [
    {
      "A4395": {
        "2": 2.0
      }
    },
    {
      "A4402": {
        "1": 1.0
      }
    }
  ],
  "Source_Delta_Socket": [
    {
      "A4395": "goal"
    },
    {
      "A4402": "goal"
    }
  ],
  "Delta_Socket_Order": [
    {
      "A4395": 1
    },
    {
      "A4402": 1
    }
  ],
  "Variable_Names": [
    {
      "A4395": [
        "x",
        "y"
      ]
    },
    {
      "A4402": [
        "n"
      ]
    }
  ],
  "Total_Claims": [
    {
      "A4395": 11
    },
    {
      "A4402": 26
    }
  ],
  "Total_Delta": [
    {
      "A4395": 1
    },
    {
      "A4402": 2
    }
  ],
  "Total_Delta_Socket": [
    {
      "A4395": 1
    },
    {
      "A4402": 1
    }
  ],
  "Max_Delta_Factor": [
    {
      "A4395": 0.91
    },
    {
      "A4402": 0.96
    }
  ],
  "Min_Delta_Factor": [
    {
      "A4395": 0.91
    },
    {
      "A4402": 0.85
    }
  ],
  "Max_Delta_Depth": [
    {
      "A4395": 10
    },
    {
      "A4402": 25
    }
  ],
  "Min_Delta_Depth": [
    {
      "A4395": 10
    },
    {
      "A4402": 22
    }
  ],
  "Claims": [
    {
      "id": "A4395_C1",
      "type": "goal",
      "expr": "find positive integers a, b, c such that (a^2, b^2) + (a, bc) + (b, ac) + (c, ab) = 199"
    },
    {
      "id": "A4395_C2",
      "type": "context",
      "expr": "(x, y) denotes the greatest common divisor of x and y"
    },
    {
      "id": "A4395_C3",
      "type": "context",
      "expr": "a, b, c are positive integers"
    },
    {
      "id": "A4395_C4",
      "type": "derived",
      "expr": "(a^2, b^2) = [gcd(a, b)]^2"
    },
    {
      "id": "A4395_C5",
      "type": "derived",
      "expr": "let d1 = gcd(a, b), d2 = gcd(b, c), d3 = gcd(a, c)"
    },
    {
      "id": "A4395_C6",
      "type": "derived",
      "expr": "(a, bc) = d1 * d3"
    },
    {
      "id": "A4395_C7",
      "type": "derived",
      "expr": "(b, ac) = d1 * d2"
    },
    {
      "id": "A4395_C8",
      "type": "derived",
      "expr": "(c, ab) = d2 * d3"
    },
    {
      "id": "A4395_C9",
      "type": "derived",
      "expr": "d1^2 + d1*d2 + d1*d3 + d2*d3 = 199"
    },
    {
      "id": "A4395_C10",
      "type": "derived",
      "expr": "a = 238, b = 238, c = 477"
    },
    {
      "id": "A4395_C11",
      "type": "final",
      "expr": "(a, b, c) = (238, 238, 477)"
    },
    {
      "id": "A4402_C1",
      "type": "derived",
      "expr": "\\sum_{k=1}^n x_k^k = n \\land \\sum_{k=1}^n k x_k = \frac{n(n+1)}{2} \\land \forall k=1\\dots n, x_k \\geq 0"
    },
    {
      "id": "A4402_C2",
      "type": "context",
      "expr": "\\sum_{k=1}^n x_k^k = n"
    },
    {
      "id": "A4402_C3",
      "type": "context",
      "expr": "\\sum_{k=1}^n k x_k = \frac{n(n+1)}{2}"
    },
    {
      "id": "A4402_C4",
      "type": "context",
      "expr": "\forall k=1\\dots n, x_k \\geq 0"
    },
    {
      "id": "A4402_C5",
      "type": "derived",
      "expr": "x_1 = \frac{n(n+1)}{2} - \\sum_{k=2}^n k x_k"
    },
    {
      "id": "A4402_C6",
      "type": "derived",
      "expr": "\\sum_{k=2}^n (x_k^k - k x_k) = n - \frac{n(n+1)}{2}"
    },
    {
      "id": "A4402_C7",
      "type": "derived",
      "expr": "n - \frac{n(n+1)}{2} = \frac{n(1-n)}{2}"
    },
    {
      "id": "A4402_C8",
      "type": "derived",
      "expr": "\\sum_{k=2}^n (x_k^k - k x_k) = \frac{n(1-n)}{2}"
    },
    {
      "id": "A4402_C9",
      "type": "derived",
      "expr": "\forall k=2\\dots n, f_k(t) = t^k - k t"
    },
    {
      "id": "A4402_C10",
      "type": "derived",
      "expr": "\forall k=2\\dots n, f_k'(t) = k(t^{k-1} - 1)"
    },
    {
      "id": "A4402_C11",
      "type": "derived",
      "expr": "\forall k=2\\dots n, f_k'(1) = 0"
    },
    {
      "id": "A4402_C12",
      "type": "derived",
      "expr": "\forall k=2\\dots n, f_k''(t) = k(k-1)t^{k-2}"
    },
    {
      "id": "A4402_C13",
      "type": "derived",
      "expr": "\forall k=2\\dots n, \forall t > 0, f_k''(t) > 0"
    },
    {
      "id": "A4402_C14",
      "type": "derived",
      "expr": "\forall k=2\\dots n, f_k \text{ is strictly convex on } (0, \\infty)"
    },
    {
      "id": "A4402_C15",
      "type": "derived",
      "expr": "\forall k=2\\dots n, \\arg\\min_{t \\geq 0} f_k(t) = 1"
    },
    {
      "id": "A4402_C16",
      "type": "derived",
      "expr": "\forall k=2\\dots n, f_k(1) = 1 - k"
    },
    {
      "id": "A4402_C17",
      "type": "derived",
      "expr": "\forall k=2\\dots n, \forall t \\geq 0, f_k(t) \\geq 1 - k \\land (= \\iff t=1)"
    },
    {
      "id": "A4402_C18",
      "type": "derived",
      "expr": "\\sum_{k=2}^n f_k(x_k) \\geq \\sum_{k=2}^n (1 - k) \\land (= \\iff \forall k=2\\dots n, x_k = 1)"
    },
    {
      "id": "A4402_C19",
      "type": "derived",
      "expr": "\\sum_{k=2}^n k = \frac{n(n+1)}{2} - 1"
    },
    {
      "id": "A4402_C20",
      "type": "derived",
      "expr": "\\sum_{k=2}^n (1 - k) = \frac{n(1-n)}{2}"
    },
    {
      "id": "A4402_C21",
      "type": "derived",
      "expr": "\\sum_{k=2}^n f_k(x_k) = \\sum_{k=2}^n f_k(1)"
    },
    {
      "id": "A4402_C22",
      "type": "derived",
      "expr": "\forall k=2\\dots n, x_k = 1"
    },
    {
      "id": "A4402_C23",
      "type": "derived",
      "expr": "x_1 + \\sum_{k=2}^n k \\cdot 1 = \frac{n(n+1)}{2}"
    },
    {
      "id": "A4402_C24",
      "type": "derived",
      "expr": "x_1 + \frac{n(n+1)}{2} - 1 = \frac{n(n+1)}{2}"
    },
    {
      "id": "A4402_C25",
      "type": "derived",
      "expr": "x_1 = 1"
    },
    {
      "id": "A4402_C26",
      "type": "final",
      "expr": "(x_1, x_2, \\dots, x_n) = (1, 1, \\dots, 1)"
    },
    {
      "id": "B8479_C1",
      "type": "goal",
      "expr": "\\sum_{k=1}^n x_k^k = n \\land \\sum_{k=1}^n k x_k = \frac{n(n+1)}{2} \\land \forall k=(c - 476)\\dots n, x_k \\geq 0"
    }
  ],
  "Steps": [
    {
      "id": "A4395_S1",
      "rule": "problem setup",
      "premises": [
        "A4395_C1: find positive integers a, b, c such that (a^2, b^2) + (a, bc) + (b, ac) + (c, ab) = 199"
      ],
      "conclusions": [
        "A4395_C2: (x, y) denotes the greatest common divisor of x and y",
        "A4395_C3: a, b, c are positive integers"
      ]
    },
    {
      "id": "A4395_S2",
      "rule": "property of gcd",
      "premises": [
        "A4395_C2: (x, y) denotes the greatest common divisor of x and y",
        "A4395_C3: a, b, c are positive integers"
      ],
      "conclusions": [
        "A4395_C4: (a^2, b^2) = [gcd(a, b)]^2"
      ]
    },
    {
      "id": "A4395_S3",
      "rule": "introduce notation",
      "premises": [
        "A4395_C3: a, b, c are positive integers"
      ],
      "conclusions": [
        "A4395_C5: let d1 = gcd(a, b), d2 = gcd(b, c), d3 = gcd(a, c)"
      ]
    },
    {
      "id": "A4395_S4",
      "rule": "gcd property under assumptions",
      "premises": [
        "A4395_C5: let d1 = gcd(a, b), d2 = gcd(b, c), d3 = gcd(a, c)",
        "A4395_C2: (x, y) denotes the greatest common divisor of x and y"
      ],
      "conclusions": [
        "A4395_C6: (a, bc) = d1 * d3"
      ]
    },
    {
      "id": "A4395_S5",
      "rule": "gcd property under assumptions",
      "premises": [
        "A4395_C5: let d1 = gcd(a, b), d2 = gcd(b, c), d3 = gcd(a, c)",
        "A4395_C2: (x, y) denotes the greatest common divisor of x and y"
      ],
      "conclusions": [
        "A4395_C7: (b, ac) = d1 * d2"
      ]
    },
    {
      "id": "A4395_S6",
      "rule": "gcd property under assumptions",
      "premises": [
        "A4395_C5: let d1 = gcd(a, b), d2 = gcd(b, c), d3 = gcd(a, c)",
        "A4395_C2: (x, y) denotes the greatest common divisor of x and y"
      ],
      "conclusions": [
        "A4395_C8: (c, ab) = d2 * d3"
      ]
    },
    {
      "id": "A4395_S7",
      "rule": "substitution",
      "premises": [
        "A4395_C4: (a^2, b^2) = [gcd(a, b)]^2",
        "A4395_C6: (a, bc) = d1 * d3",
        "A4395_C7: (b, ac) = d1 * d2",
        "A4395_C8: (c, ab) = d2 * d3",
        "A4395_C1: find positive integers a, b, c such that (a^2, b^2) + (a, bc) + (b, ac) + (c, ab) = 199"
      ],
      "conclusions": [
        "A4395_C9: d1^2 + d1*d2 + d1*d3 + d2*d3 = 199"
      ]
    },
    {
      "id": "A4395_S8",
      "rule": "proposed solution by trial",
      "premises": [
        "A4395_C9: d1^2 + d1*d2 + d1*d3 + d2*d3 = 199"
      ],
      "conclusions": [
        "A4395_C10: a = 238, b = 238, c = 477"
      ]
    },
    {
      "id": "A4395_S9",
      "rule": "specific choice",
      "premises": [
        "A4395_C10: a = 238, b = 238, c = 477"
      ],
      "conclusions": [
        "A4395_C11: (a, b, c) = (238, 238, 477)"
      ]
    },
    {
      "id": "A4402_S1",
      "rule": "problem setup",
      "premises": [
        "A4402_C1: \\sum_{k=1}^n x_k^k = n \\land \\sum_{k=1}^n k x_k = \frac{n(n+1)}{2} \\land \forall k=1\\dots n, x_k \\geq 0"
      ],
      "conclusions": [
        "A4402_C2: \\sum_{k=1}^n x_k^k = n",
        "A4402_C3: \\sum_{k=1}^n k x_k = \frac{n(n+1)}{2}",
        "A4402_C4: \forall k=1\\dots n, x_k \\geq 0"
      ]
    },
    {
      "id": "A4402_S2",
      "rule": "algebraic rearrangement",
      "premises": [
        "A4402_C3: \\sum_{k=1}^n k x_k = \frac{n(n+1)}{2}"
      ],
      "conclusions": [
        "A4402_C5: x_1 = \frac{n(n+1)}{2} - \\sum_{k=2}^n k x_k"
      ]
    },
    {
      "id": "A4402_S3",
      "rule": "substitution",
      "premises": [
        "A4402_C2: \\sum_{k=1}^n x_k^k = n",
        "A4402_C5: x_1 = \frac{n(n+1)}{2} - \\sum_{k=2}^n k x_k"
      ],
      "conclusions": [
        "A4402_C6: \\sum_{k=2}^n (x_k^k - k x_k) = n - \frac{n(n+1)}{2}"
      ]
    },
    {
      "id": "A4402_S4",
      "rule": "algebraic simplification",
      "premises": [
        "A4402_C6: \\sum_{k=2}^n (x_k^k - k x_k) = n - \frac{n(n+1)}{2}"
      ],
      "conclusions": [
        "A4402_C7: n - \frac{n(n+1)}{2} = \frac{n(1-n)}{2}"
      ]
    },
    {
      "id": "A4402_S5",
      "rule": "equivalence",
      "premises": [
        "A4402_C6: \\sum_{k=2}^n (x_k^k - k x_k) = n - \frac{n(n+1)}{2}",
        "A4402_C7: n - \frac{n(n+1)}{2} = \frac{n(1-n)}{2}"
      ],
      "conclusions": [
        "A4402_C8: \\sum_{k=2}^n (x_k^k - k x_k) = \frac{n(1-n)}{2}"
      ]
    },
    {
      "id": "A4402_S6",
      "rule": "definition",
      "premises": [
        "A4402_C8: \\sum_{k=2}^n (x_k^k - k x_k) = \frac{n(1-n)}{2}"
      ],
      "conclusions": [
        "A4402_C9: \forall k=2\\dots n, f_k(t) = t^k - k t"
      ]
    },
    {
      "id": "A4402_S7",
      "rule": "differentiation",
      "premises": [
        "A4402_C9: \forall k=2\\dots n, f_k(t) = t^k - k t"
      ],
      "conclusions": [
        "A4402_C10: \forall k=2\\dots n, f_k'(t) = k(t^{k-1} - 1)"
      ]
    },
    {
      "id": "A4402_S8",
      "rule": "evaluation at t=1",
      "premises": [
        "A4402_C10: \forall k=2\\dots n, f_k'(t) = k(t^{k-1} - 1)"
      ],
      "conclusions": [
        "A4402_C11: \forall k=2\\dots n, f_k'(1) = 0"
      ]
    },
    {
      "id": "A4402_S9",
      "rule": "differentiation",
      "premises": [
        "A4402_C10: \forall k=2\\dots n, f_k'(t) = k(t^{k-1} - 1)"
      ],
      "conclusions": [
        "A4402_C12: \forall k=2\\dots n, f_k''(t) = k(k-1)t^{k-2}"
      ]
    },
    {
      "id": "A4402_S10",
      "rule": "second derivative test",
      "premises": [
        "A4402_C12: \forall k=2\\dots n, f_k''(t) = k(k-1)t^{k-2}",
        "A4402_C4: \forall k=1\\dots n, x_k \\geq 0"
      ],
      "conclusions": [
        "A4402_C13: \forall k=2\\dots n, \forall t > 0, f_k''(t) > 0"
      ]
    },
    {
      "id": "A4402_S11",
      "rule": "strict convexity",
      "premises": [
        "A4402_C13: \forall k=2\\dots n, \forall t > 0, f_k''(t) > 0"
      ],
      "conclusions": [
        "A4402_C14: \forall k=2\\dots n, f_k \text{ is strictly convex on } (0, \\infty)"
      ]
    },
    {
      "id": "A4402_S12",
      "rule": "critical point analysis",
      "premises": [
        "A4402_C10: \forall k=2\\dots n, f_k'(t) = k(t^{k-1} - 1)",
        "A4402_C11: \forall k=2\\dots n, f_k'(1) = 0",
        "A4402_C14: \forall k=2\\dots n, f_k \text{ is strictly convex on } (0, \\infty)"
      ],
      "conclusions": [
        "A4402_C15: \forall k=2\\dots n, \\arg\\min_{t \\geq 0} f_k(t) = 1"
      ]
    },
    {
      "id": "A4402_S13",
      "rule": "evaluation at t=1",
      "premises": [
        "A4402_C9: \forall k=2\\dots n, f_k(t) = t^k - k t"
      ],
      "conclusions": [
        "A4402_C16: \forall k=2\\dots n, f_k(1) = 1 - k"
      ]
    },
    {
      "id": "A4402_S14",
      "rule": "strict convexity minimum property",
      "premises": [
        "A4402_C14: \forall k=2\\dots n, f_k \text{ is strictly convex on } (0, \\infty)",
        "A4402_C15: \forall k=2\\dots n, \\arg\\min_{t \\geq 0} f_k(t) = 1",
        "A4402_C16: \forall k=2\\dots n, f_k(1) = 1 - k"
      ],
      "conclusions": [
        "A4402_C17: \forall k=2\\dots n, \forall t \\geq 0, f_k(t) \\geq 1 - k \\land (= \\iff t=1)"
      ]
    },
    {
      "id": "A4402_S15",
      "rule": "summing inequalities",
      "premises": [
        "A4402_C17: \forall k=2\\dots n, \forall t \\geq 0, f_k(t) \\geq 1 - k \\land (= \\iff t=1)"
      ],
      "conclusions": [
        "A4402_C18: \\sum_{k=2}^n f_k(x_k) \\geq \\sum_{k=2}^n (1 - k) \\land (= \\iff \forall k=2\\dots n, x_k = 1)"
      ]
    },
    {
      "id": "A4402_S16",
      "rule": "sum formula",
      "premises": [
        "A4402_C3: \\sum_{k=1}^n k x_k = \frac{n(n+1)}{2}"
      ],
      "conclusions": [
        "A4402_C19: \\sum_{k=2}^n k = \frac{n(n+1)}{2} - 1"
      ]
    },
    {
      "id": "A4402_S17",
      "rule": "algebraic computation",
      "premises": [
        "A4402_C16: \forall k=2\\dots n, f_k(1) = 1 - k",
        "A4402_C19: \\sum_{k=2}^n k = \frac{n(n+1)}{2} - 1"
      ],
      "conclusions": [
        "A4402_C20: \\sum_{k=2}^n (1 - k) = \frac{n(1-n)}{2}"
      ]
    },
    {
      "id": "A4402_S18",
      "rule": "equality",
      "premises": [
        "A4402_C8: \\sum_{k=2}^n (x_k^k - k x_k) = \frac{n(1-n)}{2}",
        "A4402_C20: \\sum_{k=2}^n (1 - k) = \frac{n(1-n)}{2}"
      ],
      "conclusions": [
        "A4402_C21: \\sum_{k=2}^n f_k(x_k) = \\sum_{k=2}^n f_k(1)"
      ]
    },
    {
      "id": "A4402_S19",
      "rule": "equality case from strict inequality",
      "premises": [
        "A4402_C18: \\sum_{k=2}^n f_k(x_k) \\geq \\sum_{k=2}^n (1 - k) \\land (= \\iff \forall k=2\\dots n, x_k = 1)",
        "A4402_C21: \\sum_{k=2}^n f_k(x_k) = \\sum_{k=2}^n f_k(1)"
      ],
      "conclusions": [
        "A4402_C22: \forall k=2\\dots n, x_k = 1"
      ]
    },
    {
      "id": "A4402_S20",
      "rule": "substitution",
      "premises": [
        "A4402_C3: \\sum_{k=1}^n k x_k = \frac{n(n+1)}{2}",
        "A4402_C22: \forall k=2\\dots n, x_k = 1"
      ],
      "conclusions": [
        "A4402_C23: x_1 + \\sum_{k=2}^n k \\cdot 1 = \frac{n(n+1)}{2}"
      ]
    },
    {
      "id": "A4402_S21",
      "rule": "substitution",
      "premises": [
        "A4402_C23: x_1 + \\sum_{k=2}^n k \\cdot 1 = \frac{n(n+1)}{2}",
        "A4402_C19: \\sum_{k=2}^n k = \frac{n(n+1)}{2} - 1"
      ],
      "conclusions": [
        "A4402_C24: x_1 + \frac{n(n+1)}{2} - 1 = \frac{n(n+1)}{2}"
      ]
    },
    {
      "id": "A4402_S22",
      "rule": "algebraic simplification",
      "premises": [
        "A4402_C24: x_1 + \frac{n(n+1)}{2} - 1 = \frac{n(n+1)}{2}"
      ],
      "conclusions": [
        "A4402_C25: x_1 = 1"
      ]
    },
    {
      "id": "A4402_S23",
      "rule": "solution combination",
      "premises": [
        "A4402_C22: \forall k=2\\dots n, x_k = 1",
        "A4402_C25: x_1 = 1"
      ],
      "conclusions": [
        "A4402_C26: (x_1, x_2, \\dots, x_n) = (1, 1, \\dots, 1)"
      ]
    },
    {
      "id": "B8479_S1",
      "rule": "problem connection",
      "premises": [
        "B8479_C1: \\sum_{k=1}^n x_k^k = n \\land \\sum_{k=1}^n k x_k = \frac{n(n+1)}{2} \\land \forall k=(c - 476)\\dots n, x_k \\geq 0",
        "A4395_C10: a = 238, b = 238, c = 477"
      ],
      "conclusions": [
        "A4402_C1: \\sum_{k=1}^n x_k^k = n \\land \\sum_{k=1}^n k x_k = \frac{n(n+1)}{2} \\land \forall k=1\\dots n, x_k \\geq 0"
      ]
    }
  ]
}